apin/__init__.py
apin/manage.py
apin/core/DBClient.py
apin/core/__init__.py
apin/core/basecase.py
apin/core/dataParser.py
apin/core/generateCase.py
apin/core/httptest.py
apin/core/initEvn.py
apin/core/logger.py
apin/core/resultPush.py
apin/core/testResult.py
apin/core/testRunner.py
apin/core/tools.py
apin/templates/__init__.py
apin/templates/http_demo/__init__.py
apin/templates/http_demo/funcTools.py
apin/templates/http_demo/run.py
apin/templates/http_demo/settings.py
apin/templates/http_demo/case_json/__init__.py
apin/templates/http_demo/case_json/test_json_demo.json
apin/templates/http_demo/case_py/__init__.py
apin/templates/http_demo/case_py/test_case_demo.py
apin/templates/http_demo/case_yaml/__init__.py
apin/templates/http_demo/case_yaml/test_case_demo.yaml
apin/templates/http_demo/logs/__init__.py
apin/templates/http_demo/reports/__init__.py
apin/templates/logs/__init__.py
apin/templates/reports/__init__.py
apin/templates/reports/dingtalk.md
apin/templates/reports/templates03.html
apin/templates/reports/templates1.html
apin/templates/reports/templates2.html
apin/templates/reports/templates3.html
tests/2021-08-09_16_11_53report.html
tests/2021-08-09_16_26_18report.html
tests/2021-08-09_16_43_52report.html
tests/2021-08-09_16_53_45report.html
tests/2021-08-09_16_54_19report.html
tests/2021-08-09_16_58_19report.html
tests/2021-08-09_16_59_06report.html
tests/2021-08-09_16_59_33report.html
tests/2021-08-09_16_59_38report.html
tests/2021-08-09_17_03_46report.html
tests/2021-08-09_17_08_52report.html
tests/2021-08-09_17_21_20report.html
tests/2021-08-09_17_21_57report.html
tests/2021-08-09_17_22_22report.html
tests/__init__.py
tests/expand.py
tests/funcTools.py
tests/history.json
tests/run.py
tests/settings.py
tests/case_json/__init__.py
tests/case_json/test_json_qcd.json
tests/case_py/__init__.py
tests/case_py/test_stream_V3.py
tests/case_yaml/__init__.py
tests/case_yaml/test_qcd.yaml
tests/hooks/__init__.py
tests/hooks/db_check_hook.py
tests/hooks/fixture_hook.py
apin-1.2.3.dist-info/LICENSE
apin-1.2.3.dist-info/METADATA
apin-1.2.3.dist-info/WHEEL
apin-1.2.3.dist-info/entry_points.txt
apin-1.2.3.dist-info/top_level.txt
apin-1.2.3.dist-info/RECORD
