Metadata-Version: 2.1
Name: apin
Version: 1.2.3
Summary: apin 一个不用写代码的接口自动化测试框架
Home-page: https://github.com/musen123/apin
Author: MuSen
Author-email: musen_nmb@qq.com
License: UNKNOWN
Platform: UNKNOWN
Classifier: Programming Language :: Python :: 3
Requires-Python: >=3.6
Requires-Dist: Jinja2 (==3.0.3)
Requires-Dist: PyYAML (==5.3.1)
Requires-Dist: requests (==2.24.0)
Requires-Dist: requests-toolbelt (==0.9.1)
Requires-Dist: PyMySQL (==1.0.2)
Requires-Dist: rsa (==4.7.2)
Requires-Dist: jsonpath (==0.82)
Requires-Dist: pyasn1 (==0.4.8)
Requires-Dist: colorama (==0.4.4)
Requires-Dist: faker (==8.11.0)
